Design/alu.sv
module alu #(parameter WIDTH=32)(
    input logic [WIDTH-1:0] rs1,
    input logic [WIDTH-1:0] rs2,
    input logic [WIDTH-1:0] pc,
    input logic [2:0] func3,
    input logic [6:0] func7,
    input logic [6:0] opcode,

    output logic [WIDTH-1:0] alu_result,
    output logic [WIDTH-1:0] pc_plus_4,
    output logic [WIDTH-1:0] jump_target,
    output logic zero,
    output logic branch_taken
);


    localparam ALI_OP    = 7'b0010011;
    localparam AL_OP     = 7'b0110011;
    localparam MEM_WR_OP = 7'b0100011;
    localparam MEM_RD_OP = 7'b0000011;
    localparam BR_OP     = 7'b1100011;
    localparam JALR      = 7'b1100111;
    localparam LUI       = 7'b0110111;

    always_comb begin

        alu_result = '0;
        pc_plus_4 = pc + 4;
        jump_target = '0;
        branch_taken = 1'b0;

        case (opcode)
            ALI_OP: begin 
                case (func3)
                    3'b000: alu_result = $signed(rs1) + $signed(rs2);  // ADDI
                    3'b001: alu_result = rs1 << rs2[4:0];               // SLLI
                    3'b010: alu_result = ($signed(rs1) < $signed(rs2)); // SLTI
                    3'b011: alu_result = (rs1 < rs2);                   // SLTIU
                    3'b100: alu_result = rs1 ^ rs2;                     // XORI
                    3'b101: begin
                        if (func7[5])  // SRAI
                            alu_result = $signed(rs1) >>> rs2[4:0];
                        else           // SRLI
                            alu_result = rs1 >> rs2[4:0];
                    end
                    3'b110: alu_result = rs1 | rs2;                     // ORI
                    3'b111: alu_result = rs1 & rs2;                     // ANDI
                endcase
            end

            AL_OP: begin  
                case (func3)
                    3'b000: begin
                        if (func7[5])  // SUB
                            alu_result = $signed(rs1) - $signed(rs2);
                        else           // ADD
                            alu_result = $signed(rs1) + $signed(rs2);
                    end
                    3'b001: alu_result = rs1 << rs2[4:0];               // SLL
                    3'b010: alu_result = ($signed(rs1) < $signed(rs2)); // SLT
                    3'b011: alu_result = (rs1 < rs2);                   // SLTU
                    3'b100: alu_result = rs1 ^ rs2;                     // XOR
                    3'b101: begin
                        if (func7[5])  // SRA
                            alu_result = $signed(rs1) >>> rs2[4:0];
                        else           // SRL
                            alu_result = rs1 >> rs2[4:0];
                    end
                    3'b110: alu_result = rs1 | rs2;                     // OR
                    3'b111: alu_result = rs1 & rs2;                     // AND
                endcase
            end

            MEM_WR_OP, MEM_RD_OP: begin  
                alu_result = $signed(rs1) + $signed(rs2);
            end

            BR_OP: begin  
                jump_target = pc + $signed(rs2);
                case (func3)
                    3'b000: branch_taken = (rs1 == rs2);                // BEQ
                    3'b001: branch_taken = (rs1 != rs2);                // BNE
                    3'b100: branch_taken = ($signed(rs1) < $signed(rs2)); // BLT
                    3'b101: branch_taken = ($signed(rs1) >= $signed(rs2)); // BGE
                    3'b110: branch_taken = (rs1 < rs2);                  // BLTU
                    3'b111: branch_taken = (rs1 >= rs2);                 // BGEU
                endcase
            end

            JALR: begin
                alu_result = pc + 4;
                jump_target = ($signed(rs1) + $signed(rs2)) & ~1;
            end

            LUI: begin
                alu_result = rs2;
            end
        endcase
    end

    assign zero = (alu_result == '0);
endmodule

Design/alu_tb.sv
`timescale 1ns/1ps

module alu_tb;
    parameter WIDTH = 32;
    

    logic [WIDTH-1:0] rs1;
    logic [WIDTH-1:0] rs2;
    logic [WIDTH-1:0] pc;
    logic [2:0]  func3;
    logic [6:0]  func7;
    logic [6:0]  opcode;
    

    logic [WIDTH-1:0] alu_result;
    logic [WIDTH-1:0] pc_plus_4;
    logic [WIDTH-1:0] jump_target;
    logic zero;
    logic branch_taken;
    

    alu #(WIDTH) dut (
        .rs1(rs1),
        .rs2(rs2),
        .pc(pc),
        .func3(func3),
        .func7(func7),
        .opcode(opcode),
        .alu_result(alu_result),
        .pc_plus_4(pc_plus_4),
        .jump_target(jump_target),
        .zero(zero),
        .branch_taken(branch_taken)
    );
    

    localparam ALI_OP    = 7'b0010011;
    localparam AL_OP     = 7'b0110011;
    localparam MEM_WR_OP = 7'b0100011;
    localparam MEM_RD_OP = 7'b0000011;
    localparam BR_OP     = 7'b1100011;
    localparam JALR      = 7'b1100111;
    localparam LUI       = 7'b0110111;
    
    integer error_count = 0;
    
    task check_result;
        input [WIDTH-1:0] expected;
        input [WIDTH-1:0] actual;
        input string test_name;
        begin
            if (actual !== expected) begin
                $display("[ERROR] %s: Expected 0x%h, Got 0x%h", test_name, expected, actual);
                error_count = error_count + 1;
            end
            else begin
                $display("[PASS] %s: 0x%h", test_name, actual);
            end
        end
    endtask
    
    initial begin
        $display("Starting ALU testbench...");
        pc = 32'h00001000;  
        
        // Test 1: ADD (Register)
        opcode = AL_OP;
        func3 = 3'b000;
        func7 = 7'b0000000;
        rs1 = 32'h00000005;
        rs2 = 32'h00000003;
        #10;
        check_result(32'h00000008, alu_result, "ADD 5+3");
        
        // Test 2: SUB (Register)
        func7 = 7'b0100000;
        rs1 = 32'h0000000A;
        rs2 = 32'h00000004;
        #10;
        check_result(32'h00000006, alu_result, "SUB 10-4");
        
        // Test 3: ADDI (Immediate)
        opcode = ALI_OP;
        func3 = 3'b000;
        rs1 = 32'h00000005;
        rs2 = 32'h00000005;
        #10;
        check_result(32'h0000000A, alu_result, "ADDI 5+5");
        
        // Test 4: SLTI (Signed comparison)
        func3 = 3'b010;
        rs1 = 32'hFFFFFFF0;  // -16
        rs2 = 32'h00000005;  // +5
        #10;
        check_result(32'h00000001, alu_result, "SLTI -16<5");
        
        // Test 5: SRAI (Arithmetic shift right)
        func3 = 3'b101;
        func7 = 7'b0100000;
        rs1 = 32'h80000000;  // -2^31
        rs2 = 32'h00000004;  // Shift by 4
        #10;
        check_result(32'hF8000000, alu_result, "SRAI 0x80000000>>4");
        
        // Test 6: JALR
        opcode = JALR;
        pc = 32'h00001000;
        rs1 = 32'h00002000;
        rs2 = 32'h00000008;  // +8
        #10;
        check_result(32'h00001004, alu_result, "JALR return address");
        check_result(32'h00002008, jump_target & ~1, "JALR target address");
        
        // Test 7: BEQ (Branch Equal)
        opcode = BR_OP;
        func3 = 3'b000;
        pc = 32'h00002000;
        rs1 = 32'h0000000A;
        rs2 = 32'h0000000A;  // -10 (sign-extended)
        #10;
        check_result(32'h1, branch_taken, "BEQ 10==10");

        
        // Test 8: LUI
        opcode = LUI;
        rs2 = 32'h12345000;
        #10;
        check_result(32'h12345000, alu_result, "LUI");
        
        // Test 9: XOR (Register)
        opcode = AL_OP;
        func3 = 3'b100;
        rs1 = 32'hA5A5A5A5;
        rs2 = 32'h5A5A5A5A;
        #10;
        check_result(32'hFFFFFFFF, alu_result, "XOR");
        
        // Test 10: Memory address calculation
        opcode = MEM_RD_OP;
        rs1 = 32'h10001000;
        rs2 = 32'h00000FFF;  // +4095
        #10;
        check_result(32'h10001FFF, alu_result, "Load address calculation");
        
        // Summary
        if (error_count == 0) begin
            $display("ALU TESTBENCH PASSED ALL TESTS!");
        end
        else begin
            $display("ALU TESTBENCH FAILED %d TESTS!", error_count);
        end
        
        $finish;
    end
    
    initial begin
        $dumpfile("alu_waveform.vcd");
        $dumpvars(0, alu_tb);
    end
endmodule

Design/alu_waveform.vcd
$date
	Sat Jun 14 21:17:05 2025
$end
$version
	Icarus Verilog
$end
$timescale
	1ps
$end
$scope module alu_tb $end
$var wire 1 ! zero $end
$var wire 32 " pc_plus_4 [31:0] $end
$var wire 32 # jump_target [31:0] $end
$var wire 1 $ branch_taken $end
$var wire 32 % alu_result [31:0] $end
$var parameter 7 & ALI_OP $end
$var parameter 7 ' AL_OP $end
$var parameter 7 ( BR_OP $end
$var parameter 7 ) JALR $end
$var parameter 7 * LUI $end
$var parameter 7 + MEM_RD_OP $end
$var parameter 7 , MEM_WR_OP $end
$var parameter 32 - WIDTH $end
$var reg 3 . func3 [2:0] $end
$var reg 7 / func7 [6:0] $end
$var reg 7 0 opcode [6:0] $end
$var reg 32 1 pc [31:0] $end
$var reg 32 2 rs1 [31:0] $end
$var reg 32 3 rs2 [31:0] $end
$var integer 32 4 error_count [31:0] $end
$scope module dut $end
$var wire 3 5 func3 [2:0] $end
$var wire 7 6 func7 [6:0] $end
$var wire 7 7 opcode [6:0] $end
$var wire 32 8 pc [31:0] $end
$var wire 32 9 rs1 [31:0] $end
$var wire 32 : rs2 [31:0] $end
$var wire 1 ! zero $end
$var parameter 7 ; ALI_OP $end
$var parameter 7 < AL_OP $end
$var parameter 7 = BR_OP $end
$var parameter 7 > JALR $end
$var parameter 7 ? LUI $end
$var parameter 7 @ MEM_RD_OP $end
$var parameter 7 A MEM_WR_OP $end
$var parameter 32 B WIDTH $end
$var reg 32 C alu_result [31:0] $end
$var reg 1 $ branch_taken $end
$var reg 32 D jump_target [31:0] $end
$var reg 32 E pc_plus_4 [31:0] $end
$upscope $end
$scope task check_result $end
$var reg 32 F actual [31:0] $end
$var reg 32 G expected [31:0] $end
$upscope $end
$upscope $end
$enddefinitions $end
$comment Show the parameter values. $end
$dumpall
b100000 B
b100011 A
b11 @
b110111 ?
b1100111 >
b1100011 =
b110011 <
b10011 ;
b100000 -
b100011 ,
b11 +
b110111 *
b1100111 )
b1100011 (
b110011 '
b10011 &
$end
#0
$dumpvars
bx G
bx F
b1000000000100 E
b0 D
b1000 C
b11 :
b101 9
b1000000000000 8
b110011 7
b0 6
b0 5
b0 4
b11 3
b101 2
b1000000000000 1
b110011 0
b0 /
b0 .
b1000 %
0$
b0 #
b1000000000100 "
0!
$end
#10000
0!
b110 %
b110 C
b100 3
b100 :
b1010 2
b1010 9
b100000 /
b100000 6
b1000 F
b1000 G
#20000
0!
b1010 %
b1010 C
b101 3
b101 :
b101 2
b101 9
b10011 0
b10011 7
b110 F
b110 G
#30000
0!
b1 %
b1 C
b11111111111111111111111111110000 2
b11111111111111111111111111110000 9
b10 .
b10 5
b1010 F
b1010 G
#40000
0!
b11111000000000000000000000000000 %
b11111000000000000000000000000000 C
b100 3
b100 :
b10000000000000000000000000000000 2
b10000000000000000000000000000000 9
b101 .
b101 5
b1 F
b1 G
#50000
b10000000001000 #
b10000000001000 D
0!
b1000000000100 %
b1000000000100 C
b1000 3
b1000 :
b10000000000000 2
b10000000000000 9
b1100111 0
b1100111 7
b11111000000000000000000000000000 F
b11111000000000000000000000000000 G
#60000
1$
b10000000001010 #
b10000000001010 D
b10000000000100 "
b10000000000100 E
1!
b0 %
b0 C
b1010 3
b1010 :
b1010 2
b1010 9
b10000000000000 1
b10000000000000 8
b0 .
b0 5
b1100011 0
b1100011 7
b10000000001000 F
b10000000001000 G
#70000
0!
b10010001101000101000000000000 %
b10010001101000101000000000000 C
0$
b0 #
b0 D
b10010001101000101000000000000 3
b10010001101000101000000000000 :
b110111 0
b110111 7
b1 F
b1 G
#80000
0!
b11111111111111111111111111111111 %
b11111111111111111111111111111111 C
b1011010010110100101101001011010 3
b1011010010110100101101001011010 :
b10100101101001011010010110100101 2
b10100101101001011010010110100101 9
b100 .
b100 5
b110011 0
b110011 7
b10010001101000101000000000000 F
b10010001101000101000000000000 G
#90000
0!
b10000000000000001111111111111 %
b10000000000000001111111111111 C
b111111111111 3
b111111111111 :
b10000000000000001000000000000 2
b10000000000000001000000000000 9
b11 0
b11 7
b11111111111111111111111111111111 F
b11111111111111111111111111111111 G
#100000
b10000000000000001111111111111 F
b10000000000000001111111111111 G
