Design/fsm_control.sv
module control(
    input  logic clk,
    input  logic rst,
    input  logic BW, BR, PW, PR, S,
    output logic [1:0] status
);

    // Estados
    parameter MODIFIED  = 2'd0;
    parameter EXCLUSIVE = 2'd1;
    parameter SHARED    = 2'd2;
    parameter INVALID   = 2'd3;

    logic [1:0] c_state, n_state;

    // Registro de estado actual
    always_ff @(posedge clk) begin
        if (rst) begin
            c_state <= INVALID;
        end else begin 
            c_state <= n_state;
        end
    end

    // Lógica de transición de estado
    always_comb @(state, bw) begin
        n_state = c_state;  // Por defecto, mantener estado

        case (c_state)
            MODIFIED: begin
                if (BW)      n_state = INVALID;
                else if (BR) n_state = SHARED;
                else if (PR || PW) n_state = MODIFIED;
            end

            EXCLUSIVE: begin
                if (PW)      n_state = MODIFIED;
                else if (BR) n_state = SHARED;
                else if (PR) n_state = EXCLUSIVE;
                else if (BW) n_state = INVALID;
            end

            SHARED: begin
                if (BW)      n_state = INVALID;
                else if (PW) n_state = EXCLUSIVE;
                else if (PR || BR) n_state = SHARED;
            end

            INVALID: begin
                if (PW && ~S) n_state = MODIFIED;
                else if (PR && S)  n_state = SHARED;
                else if ((PR && ~S) || (PW && S)) n_state = EXCLUSIVE;
                else if (BW || BR) n_state = INVALID;
            end
        endcase
    end

    // Asignación de estado de salida
    always_comb begin
        case (c_state)
            MODIFIED  : status = MODIFIED;
            EXCLUSIVE : status = EXCLUSIVE;
            SHARED    : status = SHARED;
            INVALID   : status = INVALID;
            default   : status = INVALID;
        endcase
    end

endmodule

Design/fsm_control_tb.sv
`timescale 1ps/1ps

module fsm_control_tb;

    // Entradas
    reg clk_tb;
    reg rst_tb;
    reg BW_tb;
    reg BR_tb;
    reg PW_tb;
    reg PR_tb;
    reg S_tb;

    // Salida
    wire [1:0] status_tb;

    // Instancia del módulo
    control dut (
        .clk(clk_tb),
        .rst(rst_tb),
        .BW(BW_tb),
        .BR(BR_tb),
        .PW(PW_tb),
        .PR(PR_tb),
        .S(S_tb),
        .status(status_tb)
    );

    // Reloj
    always begin
        #5 clk_tb = ~clk_tb;
    end

    // Estímulos
    initial begin
        $dumpfile("control.vcd");
        $dumpvars(0, fsm_control_tb);

        clk_tb = 0;
        rst_tb = 1; BW_tb = 0; BR_tb = 0; PR_tb = 0; PW_tb = 0; S_tb = 0;
        #10;

        rst_tb = 0; BW_tb = 1; BR_tb = 0; PR_tb = 0; PW_tb = 0; S_tb = 0;
        #20;

        BW_tb = 0; BR_tb = 0; PR_tb = 0; PW_tb = 1; S_tb = 0;
        #20;

        BW_tb = 0; BR_tb = 1; PR_tb = 0; PW_tb = 0; S_tb = 0;
        #20;

        BW_tb = 0; BR_tb = 0; PR_tb = 1; PW_tb = 0; S_tb = 1;
        #100;

        $finish;
    end

endmodule

Design/control.vcd
$date
	Wed Jun 18 16:57:19 2025
$end
$version
	Icarus Verilog
$end
$timescale
	1ps
$end
$scope module fsm_control_tb $end
$var wire 2 ! status_tb [1:0] $end
$var reg 1 " BR_tb $end
$var reg 1 # BW_tb $end
$var reg 1 $ PR_tb $end
$var reg 1 % PW_tb $end
$var reg 1 & S_tb $end
$var reg 1 ' clk_tb $end
$var reg 1 ( rst_tb $end
$scope module dut $end
$var wire 1 " BR $end
$var wire 1 # BW $end
$var wire 1 $ PR $end
$var wire 1 % PW $end
$var wire 1 & S $end
$var wire 1 ' clk $end
$var wire 1 ( rst $end
$var parameter 2 ) EXCLUSIVE $end
$var parameter 2 * INVALID $end
$var parameter 2 + MODIFIED $end
$var parameter 2 , SHARED $end
$var reg 2 - c_state [1:0] $end
$var reg 2 . n_state [1:0] $end
$var reg 2 / status [1:0] $end
$upscope $end
$upscope $end
$enddefinitions $end
$comment Show the parameter values. $end
$dumpall
b10 ,
b0 +
b11 *
b1 )
$end
#0
$dumpvars
b11 /
bx .
bx -
1(
0'
0&
0%
0$
0#
0"
b11 !
$end
#5
b11 .
b11 -
1'
#10
0'
1#
0(
#15
1'
#20
0'
#25
1'
#30
b0 .
0'
1%
0#
#35
b0 !
b0 /
b0 -
1'
#40
0'
#45
1'
#50
b10 .
0'
0%
1"
#55
b10 !
b10 /
b10 -
1'
#60
0'
#65
1'
#70
0'
1&
1$
0"
