Design/register.sv
module register #(parameter WIDTH=32)
(

    input logic clk,
    input logic rst,
    input logic write,
    input logic enable,
    input logic [WIDTH-1:0] data_in,
    
    output logic [WIDTH-1:0] data_out

);

    logic [WIDTH-1:0] reg_data;

    always_ff @( posedge clk ) begin //negedge para flancos negativos
        if (rst == 1) reg_data <= 0;

        else begin
            if (write) 
                reg_data <= data_in;
            else
                reg_data <= reg_data;

            if (enable)
                data_out <= reg_data;
            else
                data_out <= 'hz;

        end


        
    end

endmodule

Design/register_tb.sv
`timescale 1ps/1ps

module register_tb;
    
    reg  clk_tb;
    reg  rst_tb;
    reg  write_tb;
    reg  enable_tb;
    reg  [31:0] data_in_tb;
    reg  [15:0] data_in_tb1;
    
    wire  [31:0] data_out_tb;
    wire  [15:0] data_out_tb1;

    register dut (
        .clk(clk_tb),
        .rst(rst_tb),
        .write(write_tb),
        .enable(enable_tb),
        .data_in(data_in_tb),
        .data_out(data_out_tb)
    );

    register #(.WIDTH(16)) dut2 (
        .clk(clk_tb),
        .rst(rst_tb),
        .write(write_tb),
        .enable(enable_tb),
        .data_in(data_in_tb1),
        .data_out(data_out_tb1)
    );

    always begin
        #5 clk_tb = !clk_tb;
    end

    initial begin
        $dumpfile("register.vcd");
        $dumpvars(0, register_tb);  

        clk_tb = 0;

        rst_tb = 0; write_tb = 0; enable_tb = 0; data_in_tb = 0; data_in_tb1 = 0;
        #10;
        rst_tb = 1; write_tb = 0; enable_tb = 0; data_in_tb = 0; data_in_tb1 = 0;
        #10;
        rst_tb = 0; write_tb = 0; enable_tb = 0; data_in_tb = 0; data_in_tb1 = 0;
        #20;
        rst_tb = 0; write_tb = 1; enable_tb = 0; data_in_tb = 25; data_in_tb1 = 30;
        #30;
        rst_tb = 0; write_tb = 0; enable_tb = 0; data_in_tb = 40; data_in_tb1 = 40;
        #20;
        rst_tb = 0; write_tb = 0; enable_tb = 1; data_in_tb = 62; data_in_tb1 = 0;
        #20;
        rst_tb = 0; write_tb = 0; enable_tb = 1; data_in_tb = 10; data_in_tb1 = 0;
        #100;
        $finish;
    end

endmodule

Design/register.vcd
$date
	Wed May 21 21:15:46 2025
$end
$version
	Icarus Verilog
$end
$timescale
	1ps
$end
$scope module register_tb $end
$var wire 16 ! data_out_tb1 [15:0] $end
$var wire 32 " data_out_tb [31:0] $end
$var reg 1 # clk_tb $end
$var reg 32 $ data_in_tb [31:0] $end
$var reg 16 % data_in_tb1 [15:0] $end
$var reg 1 & enable_tb $end
$var reg 1 ' rst_tb $end
$var reg 1 ( write_tb $end
$scope module dut $end
$var wire 1 # clk $end
$var wire 32 ) data_in [31:0] $end
$var wire 1 & enable $end
$var wire 1 ' rst $end
$var wire 1 ( write $end
$var parameter 32 * WIDTH $end
$var reg 32 + data_out [31:0] $end
$var reg 32 , reg_data [31:0] $end
$upscope $end
$scope module dut2 $end
$var wire 1 # clk $end
$var wire 16 - data_in [15:0] $end
$var wire 1 & enable $end
$var wire 1 ' rst $end
$var wire 1 ( write $end
$var parameter 32 . WIDTH $end
$var reg 16 / data_out [15:0] $end
$var reg 16 0 reg_data [15:0] $end
$upscope $end
$upscope $end
$enddefinitions $end
$comment Show the parameter values. $end
$dumpall
b10000 .
b100000 *
$end
#0
$dumpvars
bx 0
bx /
b0 -
bx ,
bx +
b0 )
0(
0'
0&
b0 %
b0 $
0#
bx "
bx !
$end
#5
bz "
bz +
bz !
bz /
1#
#10
0#
1'
#15
b0 0
b0 ,
1#
#20
0#
0'
#25
1#
#30
0#
#35
1#
#40
0#
b11110 %
b11110 -
b11001 $
b11001 )
1(
#45
b11001 ,
b11110 0
1#
#50
0#
#55
1#
#60
0#
#65
1#
#70
0#
b101000 %
b101000 -
b101000 $
b101000 )
0(
#75
1#
#80
0#
#85
1#
#90
0#
b0 %
b0 -
b111110 $
b111110 )
1&
#95
b11110 !
b11110 /
b11001 "
b11001 +
1#
#100
0#
#105
1#
#110
0#
b1010 $
b1010 )
